polymr/__init__.py
polymr/featurizers.py
polymr/index.py
polymr/query.py
polymr/record.py
polymr/score.py
polymr/storage.py
polymr/util.py
polymr-1.0.0.dist-info/DESCRIPTION.rst
polymr-1.0.0.dist-info/METADATA
polymr-1.0.0.dist-info/RECORD
polymr-1.0.0.dist-info/WHEEL
polymr-1.0.0.dist-info/entry_points.txt
polymr-1.0.0.dist-info/metadata.json
polymr-1.0.0.dist-info/top_level.txt
