Metadata-Version: 2.0
Name: polymr
Version: 1.0.0
Summary: Index and search lots of small documents
Home-page: https://github.com/massmutual/polymr
Author: Randall Schwager
Author-email: rschwager@massmutual.com
License: Apache Software License
Project-URL: Documentation, https://github.com/massmutual/polymr
Project-URL: Tracker, https://github.com/massmutual/polymr/issues
Keywords: search python leveldb kmer-based
Platform: UNKNOWN
Classifier: Development Status :: 4 - Beta
Classifier: License :: OSI Approved :: Apache Software License
Classifier: Operating System :: POSIX
Classifier: Programming Language :: Python :: 3
Classifier: Topic :: Database
Classifier: Topic :: Internet :: WWW/HTTP :: Indexing/Search
Requires-Python: >=3
Requires-Dist: leveldb
Requires-Dist: toolz
Requires-Dist: msgpack-python
